gguf/__init__.py
gguf/constants.py
gguf/gguf.py
gguf/gguf_reader.py
gguf/gguf_writer.py
gguf/lazy.py
gguf/metadata.py
gguf/py.typed
gguf/quants.py
gguf/scripts/gguf_convert_endian.py
gguf/scripts/gguf_dump.py
gguf/scripts/gguf_editor_gui.py
gguf/scripts/gguf_hash.py
gguf/scripts/gguf_new_metadata.py
gguf/scripts/gguf_set_metadata.py
gguf/tensor_mapping.py
gguf/utility.py
gguf/vocab.py
gguf-0.17.0.dist-info/LICENSE
gguf-0.17.0.dist-info/METADATA
gguf-0.17.0.dist-info/WHEEL
gguf-0.17.0.dist-info/entry_points.txt
gguf-0.17.0.dist-info/RECORD
